azure/ai/language/questionanswering/__init__.py
azure/ai/language/questionanswering/_configuration.py
azure/ai/language/questionanswering/_patch.py
azure/ai/language/questionanswering/_question_answering_client.py
azure/ai/language/questionanswering/_version.py
azure/ai/language/questionanswering/_operations/__init__.py
azure/ai/language/questionanswering/_operations/_operations.py
azure/ai/language/questionanswering/aio/__init__.py
azure/ai/language/questionanswering/aio/_configuration.py
azure/ai/language/questionanswering/aio/_question_answering_client.py
azure/ai/language/questionanswering/aio/_operations/__init__.py
azure/ai/language/questionanswering/aio/_operations/_operations.py
azure/ai/language/questionanswering/models/__init__.py
azure/ai/language/questionanswering/models/_models.py
azure/ai/language/questionanswering/models/_models_py3.py
azure/ai/language/questionanswering/models/_question_answering_client_enums.py
azure_ai_language_questionanswering-1.0.0.dist-info/METADATA
azure_ai_language_questionanswering-1.0.0.dist-info/WHEEL
azure_ai_language_questionanswering-1.0.0.dist-info/top_level.txt
azure_ai_language_questionanswering-1.0.0.dist-info/RECORD
