Metadata-Version: 2.1
Name: azure-ai-language-questionanswering
Version: 1.0.0
Summary: Microsoft Azure Question Answering Client Library for Python
Home-page: https://github.com/Azure/azure-sdk-for-python
Author: Microsoft Corporation
Author-email: azuresdkengsysadmins@microsoft.com
License: MIT License
Project-URL: Bug Reports, https://github.com/Azure/azure-sdk-for-python/issues
Project-URL: Source, https://github.com/Azure/azure-sdk-python
Platform: UNKNOWN
Classifier: Development Status :: 5 - Production/Stable
Classifier: Programming Language :: Python
Classifier: Programming Language :: Python :: 2
Classifier: Programming Language :: Python :: 2.7
Classifier: Programming Language :: Python :: 3
Classifier: Programming Language :: Python :: 3.6
Classifier: Programming Language :: Python :: 3.7
Classifier: Programming Language :: Python :: 3.8
Classifier: Programming Language :: Python :: 3.9
Classifier: Programming Language :: Python :: 3.10
Classifier: License :: OSI Approved :: MIT License
Requires-Dist: azure-core (<2.0.0,>=1.19.1)
Requires-Dist: msrest (>=0.6.21)
Requires-Dist: futures ; python_version<'3.0'
Requires-Dist: azure-ai-language-nspkg ; python_version<'3.0'
Requires-Dist: typing ; python_version<'3.5'
